<annotation>
  <folder>img</folder>
  <filename>img20170303_1074</filename>
  <path>/home/ruqiang/github/CR_AI/data/img/img20170303_1074.jpg</path>
  <source>
    <database>Unknown</database>
  </source>
  <size>
    <width>1280</width>
    <height>720</height>
    <depth>3</depth>
  </size>
  <segmented>0</segmented>
  <object>
    <name>musketeer</name>
    <pose>Unspecified</pose>
    <truncated>0</truncated>
    <difficult>0</difficult>
    <bndbox>
      <xmin>658</xmin>
      <ymin>479</ymin>
      <xmax>706</xmax>
      <ymax>508</ymax>
    </bndbox>
  </object>
  <object>
    <name>witch</name>
    <pose>Unspecified</pose>
    <truncated>0</truncated>
    <difficult>0</difficult>
    <bndbox>
      <xmin>650</xmin>
      <ymin>504</ymin>
      <xmax>724</xmax>
      <ymax>536</ymax>
    </bndbox>
  </object>
  <object>
    <name>king</name>
    <pose>Unspecified</pose>
    <truncated>0</truncated>
    <difficult>0</difficult>
    <bndbox>
      <xmin>429</xmin>
      <ymin>304</ymin>
      <xmax>524</xmax>
      <ymax>385</ymax>
    </bndbox>
  </object>
  <object>
    <name>eking</name>
    <pose>Unspecified</pose>
    <truncated>0</truncated>
    <difficult>0</difficult>
    <bndbox>
      <xmin>937</xmin>
      <ymin>312</ymin>
      <xmax>1040</xmax>
      <ymax>390</ymax>
    </bndbox>
  </object>
  <object>
    <name>arena</name>
    <pose>Unspecified</pose>
    <truncated>0</truncated>
    <difficult>0</difficult>
    <bndbox>
      <xmin>509</xmin>
      <ymin>182</ymin>
      <xmax>583</xmax>
      <ymax>246</ymax>
    </bndbox>
  </object>
  <object>
    <name>arena</name>
    <pose>Unspecified</pose>
    <truncated>0</truncated>
    <difficult>0</difficult>
    <bndbox>
      <xmin>499</xmin>
      <ymin>450</ymin>
      <xmax>579</xmax>
      <ymax>513</ymax>
    </bndbox>
  </object>
  <object>
    <name>earena</name>
    <pose>Unspecified</pose>
    <truncated>0</truncated>
    <difficult>0</difficult>
    <bndbox>
      <xmin>879</xmin>
      <ymin>459</ymin>
      <xmax>963</xmax>
      <ymax>519</ymax>
    </bndbox>
  </object>
  <object>
    <name>earena</name>
    <pose>Unspecified</pose>
    <truncated>0</truncated>
    <difficult>0</difficult>
    <bndbox>
      <xmin>872</xmin>
      <ymin>184</ymin>
      <xmax>956</xmax>
      <ymax>247</ymax>
    </bndbox>
  </object>
  <object>
    <name>speargoblins</name>
    <pose>Unspecified</pose>
    <truncated>0</truncated>
    <difficult>0</difficult>
    <bndbox>
      <xmin>787</xmin>
      <ymin>459</ymin>
      <xmax>858</xmax>
      <ymax>522</ymax>
    </bndbox>
  </object>
</annotation>
