<annotation>
  <folder>img</folder>
  <filename>filename_412</filename>
  <path>/home/ruqiang/github/CR_AI/data/img/filename_412.jpg</path>
  <source>
    <database>Unknown</database>
  </source>
  <size>
    <width>1280</width>
    <height>720</height>
    <depth>3</depth>
  </size>
  <segmented>0</segmented>
  <object>
    <name>king</name>
    <pose>Unspecified</pose>
    <truncated>0</truncated>
    <difficult>0</difficult>
    <bndbox>
      <xmin>466</xmin>
      <ymin>315</ymin>
      <xmax>562</xmax>
      <ymax>397</ymax>
    </bndbox>
  </object>
  <object>
    <name>eking</name>
    <pose>Unspecified</pose>
    <truncated>0</truncated>
    <difficult>0</difficult>
    <bndbox>
      <xmin>983</xmin>
      <ymin>323</ymin>
      <xmax>1088</xmax>
      <ymax>407</ymax>
    </bndbox>
  </object>
  <object>
    <name>arena</name>
    <pose>Unspecified</pose>
    <truncated>0</truncated>
    <difficult>0</difficult>
    <bndbox>
      <xmin>538</xmin>
      <ymin>192</ymin>
      <xmax>621</xmax>
      <ymax>251</ymax>
    </bndbox>
  </object>
  <object>
    <name>earena</name>
    <pose>Unspecified</pose>
    <truncated>0</truncated>
    <difficult>0</difficult>
    <bndbox>
      <xmin>923</xmin>
      <ymin>199</ymin>
      <xmax>1002</xmax>
      <ymax>255</ymax>
    </bndbox>
  </object>
  <object>
    <name>earena</name>
    <pose>Unspecified</pose>
    <truncated>0</truncated>
    <difficult>0</difficult>
    <bndbox>
      <xmin>916</xmin>
      <ymin>471</ymin>
      <xmax>997</xmax>
      <ymax>530</ymax>
    </bndbox>
  </object>
  <object>
    <name>darena</name>
    <pose>Unspecified</pose>
    <truncated>0</truncated>
    <difficult>0</difficult>
    <bndbox>
      <xmin>533</xmin>
      <ymin>462</ymin>
      <xmax>593</xmax>
      <ymax>535</ymax>
    </bndbox>
  </object>
  <object>
    <name>prince</name>
    <pose>Unspecified</pose>
    <truncated>0</truncated>
    <difficult>0</difficult>
    <bndbox>
      <xmin>436</xmin>
      <ymin>400</ymin>
      <xmax>509</xmax>
      <ymax>440</ymax>
    </bndbox>
  </object>
</annotation>
