<annotation>
  <folder>img</folder>
  <filename>img20170303_1286</filename>
  <path>/home/ruqiang/github/CR_AI/tmp_data/img/img20170303_1286.jpg</path>
  <source>
    <database>Unknown</database>
  </source>
  <size>
    <width>1280</width>
    <height>720</height>
    <depth>3</depth>
  </size>
  <segmented>0</segmented>
  <object>
    <name>giant</name>
    <pose>Unspecified</pose>
    <truncated>0</truncated>
    <difficult>0</difficult>
    <bndbox>
      <xmin>989</xmin>
      <ymin>361</ymin>
      <xmax>1066</xmax>
      <ymax>420</ymax>
    </bndbox>
  </object>
  <object>
    <name>king</name>
    <pose>Unspecified</pose>
    <truncated>0</truncated>
    <difficult>0</difficult>
    <bndbox>
      <xmin>425</xmin>
      <ymin>304</ymin>
      <xmax>523</xmax>
      <ymax>386</ymax>
    </bndbox>
  </object>
  <object>
    <name>eking</name>
    <pose>Unspecified</pose>
    <truncated>0</truncated>
    <difficult>0</difficult>
    <bndbox>
      <xmin>944</xmin>
      <ymin>312</ymin>
      <xmax>1044</xmax>
      <ymax>395</ymax>
    </bndbox>
  </object>
  <object>
    <name>arena</name>
    <pose>Unspecified</pose>
    <truncated>0</truncated>
    <difficult>0</difficult>
    <bndbox>
      <xmin>498</xmin>
      <ymin>450</ymin>
      <xmax>580</xmax>
      <ymax>511</ymax>
    </bndbox>
  </object>
  <object>
    <name>darena</name>
    <pose>Unspecified</pose>
    <truncated>0</truncated>
    <difficult>0</difficult>
    <bndbox>
      <xmin>503</xmin>
      <ymin>181</ymin>
      <xmax>560</xmax>
      <ymax>245</ymax>
    </bndbox>
  </object>
  <object>
    <name>earena</name>
    <pose>Unspecified</pose>
    <truncated>0</truncated>
    <difficult>0</difficult>
    <bndbox>
      <xmin>873</xmin>
      <ymin>188</ymin>
      <xmax>956</xmax>
      <ymax>247</ymax>
    </bndbox>
  </object>
  <object>
    <name>earena</name>
    <pose>Unspecified</pose>
    <truncated>0</truncated>
    <difficult>0</difficult>
    <bndbox>
      <xmin>873</xmin>
      <ymin>456</ymin>
      <xmax>956</xmax>
      <ymax>519</ymax>
    </bndbox>
  </object>
</annotation>
